snowpy/__init__.py
snowpy/datatools.py
snowpy/emailtools.py
snowpy/ocrtools.py
snowpy/process.py
snowpy-0.1.3.dist-info/LICENSE
snowpy-0.1.3.dist-info/METADATA
snowpy-0.1.3.dist-info/WHEEL
snowpy-0.1.3.dist-info/top_level.txt
snowpy-0.1.3.dist-info/RECORD
