Metadata-Version: 2.1
Name: snowpy
Version: 0.1.3
Summary: A Python library to upload and download data from database systems
Home-page: https://mltoolkit.github.io/SnowPy
Author: Sumudu Tennakoon
Author-email: mltoolkitproject@gmail.com
License: Apache License Version 2.0
Platform: UNKNOWN
Classifier: Development Status :: 3 - Alpha
Classifier: Environment :: Console
Classifier: Intended Audience :: Science/Research
Classifier: Intended Audience :: Education
Classifier: Intended Audience :: Developers
Classifier: License :: OSI Approved :: Apache Software License
Classifier: Operating System :: OS Independent
Classifier: Programming Language :: Python
Classifier: Operating System :: OS Independent
Classifier: Topic :: Scientific/Engineering
Classifier: Topic :: Software Development
Requires-Dist: numpy
Requires-Dist: scipy
Requires-Dist: pyodbc
Requires-Dist: pandas
Requires-Dist: sqlalchemy
Requires-Dist: pymltoolkit
Requires-Dist: snowflake-sqlalchemy
Requires-Dist: snowflake-connector-python
